miniperscache/__init__.py
miniperscache/arg_hasher.py
miniperscache/batched_cache.py
miniperscache/cache.py
miniperscache/logging.py
miniperscache/py.typed
miniperscache/serializer.py
miniperscache/storage.py
miniperscache-0.1.3.dist-info/METADATA
miniperscache-0.1.3.dist-info/WHEEL
miniperscache-0.1.3.dist-info/licenses/LICENSE
miniperscache-0.1.3.dist-info/RECORD
