Metadata-Version: 2.4
Name: miniperscache
Version: 0.1.3
Summary: miniperscache is a small Python library for persistent caching of function results.
Author-email: Zygimantas Straznickas <hi@zygi.me>
License-File: LICENSE
Requires-Python: >=3.10
Requires-Dist: cloudpickle>=3.1.1
Requires-Dist: dill>=0.3.9
Requires-Dist: stablehash>=0.2.1
Requires-Dist: typing-extensions>=4.12.2
